pyTGR/__init__.py
pyTGR-2.0.1.dist-info/LICENSE.txt
pyTGR-2.0.1.dist-info/METADATA
pyTGR-2.0.1.dist-info/WHEEL
pyTGR-2.0.1.dist-info/top_level.txt
pyTGR-2.0.1.dist-info/RECORD
