Metadata-Version: 2.1
Name: pyTGR
Version: 2.0.1
Summary: A minimal lib for rendering things on Terminal.
Home-page: https://github.com/mastercodermerwin/TGR
Author: Merwin
Author-email: <merwinmathews1001@gmail.com>
License: MIT
Project-URL: Bug Tracker, https://github.com/mastercodermerwin/TGR/issues
Keywords: python,terminal,color,graphics,shapes,terminal events
Platform: UNKNOWN
Classifier: Development Status :: 1 - Planning
Classifier: Intended Audience :: Developers
Classifier: Programming Language :: Python :: 3
Classifier: Operating System :: Unix
Classifier: Operating System :: MacOS :: MacOS X
Classifier: Operating System :: Microsoft :: Windows
Requires-Dist: opencv-python
Requires-Dist: pynput
Requires-Dist: sty
